conf_publisher/page_dumper.py
conf_publisher/publish.py
conf_publisher/constants.py
conf_publisher/confluence_api.py
conf_publisher/page_maker.py
conf_publisher/config.py
conf_publisher/errors.py
conf_publisher/confluence.py
conf_publisher/__init__.py
conf_publisher/data_providers/sphinx_base_data_provider.py
conf_publisher/data_providers/sphinx_fjson_data_provider.py
conf_publisher/data_providers/sphinx_html_data_provider.py
conf_publisher/data_providers/__init__.py
conf_publisher/serializers/yaml_serializer.py
conf_publisher/serializers/json_serializer.py
conf_publisher/serializers/__init__.py
conf_publisher/mutators/page_mutator.py
conf_publisher/mutators/__init__.py
confluence_publisher-1.2.1.dist-info/entry_points.txt
confluence_publisher-1.2.1.dist-info/RECORD
confluence_publisher-1.2.1.dist-info/DESCRIPTION.rst
confluence_publisher-1.2.1.dist-info/top_level.txt
confluence_publisher-1.2.1.dist-info/METADATA
confluence_publisher-1.2.1.dist-info/WHEEL
confluence_publisher-1.2.1.dist-info/metadata.json
