Metadata-Version: 2.0
Name: confluence-publisher
Version: 1.2.1
Summary: Tool for publishing Sphinx generated documents to Confluence
Home-page: https://github.com/Arello-Mobile/confluence-publisher
Author: Arello Mobile
Author-email: UNKNOWN
License: MIT
Platform: UNKNOWN
Classifier: Development Status :: 4 - Beta
Classifier: Environment :: Console
Classifier: Intended Audience :: Developers
Classifier: License :: OSI Approved :: MIT License
Classifier: Operating System :: OS Independent
Classifier: Programming Language :: Python :: 2.7
Classifier: Programming Language :: Python :: 3.3
Classifier: Programming Language :: Python :: 3.4
Classifier: Programming Language :: Python :: 3.5
Classifier: Topic :: Software Development :: Documentation
Requires-Dist: argparse (>=1.2.1)
Requires-Dist: PyYAML (>=3.11)
Requires-Dist: requests (>=2.4.3)
